odoo8_addon_web_widget_float_formula-8.0.1.0.0-py2.7-nspkg.pth
odoo_addons/web_widget_float_formula/__openerp__.py
odoo_addons/web_widget_float_formula/__init__.py
odoo_addons/web_widget_float_formula/README.rst
odoo_addons/web_widget_float_formula/views/qweb.xml
odoo_addons/web_widget_float_formula/static/description/icon.png
odoo_addons/web_widget_float_formula/static/src/js/models.js
odoo8_addon_web_widget_float_formula-8.0.1.0.0.dist-info/top_level.txt
odoo8_addon_web_widget_float_formula-8.0.1.0.0.dist-info/WHEEL
odoo8_addon_web_widget_float_formula-8.0.1.0.0.dist-info/RECORD
odoo8_addon_web_widget_float_formula-8.0.1.0.0.dist-info/metadata.json
odoo8_addon_web_widget_float_formula-8.0.1.0.0.dist-info/DESCRIPTION.rst
odoo8_addon_web_widget_float_formula-8.0.1.0.0.dist-info/METADATA
odoo8_addon_web_widget_float_formula-8.0.1.0.0.dist-info/namespace_packages.txt
